{
  "id" : "Zqr5sgqKY1PXC8HiaS71l",
  "name" : "Zqr5sgqKY1PXC8HiaS71l",
  "component" : "SchemaTransform",
  "transformations" : [ {
    "sources" : [ {
      "port" : "IPn2XUO-k-yjwvqi_DNuf",
      "name" : "acc_id",
      "exprId" : 3893
    } ],
    "destination" : {
      "port" : "Dz0WcZT7Bz1oPjYYQdwGn",
      "name" : "acc_id",
      "exprId" : 3893
    }
  }, {
    "sources" : [ {
      "port" : "IPn2XUO-k-yjwvqi_DNuf",
      "name" : "tran_id",
      "exprId" : 3894
    } ],
    "destination" : {
      "port" : "Dz0WcZT7Bz1oPjYYQdwGn",
      "name" : "tran_id",
      "exprId" : 3894
    }
  }, {
    "sources" : [ {
      "port" : "IPn2XUO-k-yjwvqi_DNuf",
      "name" : "business_date",
      "exprId" : 3895
    } ],
    "destination" : {
      "port" : "Dz0WcZT7Bz1oPjYYQdwGn",
      "name" : "business_date",
      "exprId" : 3895
    }
  }, {
    "sources" : [ {
      "port" : "IPn2XUO-k-yjwvqi_DNuf",
      "name" : "tran_amount",
      "exprId" : 3896
    } ],
    "destination" : {
      "port" : "Dz0WcZT7Bz1oPjYYQdwGn",
      "name" : "tran_amount",
      "exprId" : 3896
    }
  }, {
    "sources" : [ {
      "port" : "IPn2XUO-k-yjwvqi_DNuf",
      "name" : "tran_type",
      "exprId" : 3897
    } ],
    "destination" : {
      "port" : "Dz0WcZT7Bz1oPjYYQdwGn",
      "name" : "tran_type",
      "exprId" : 3897
    }
  }, {
    "sources" : [ {
      "port" : "IPn2XUO-k-yjwvqi_DNuf",
      "name" : "tran_ts",
      "exprId" : 3898
    } ],
    "destination" : {
      "port" : "Dz0WcZT7Bz1oPjYYQdwGn",
      "name" : "tran_ts",
      "exprId" : 3898
    }
  }, {
    "sources" : [ {
      "port" : "IPn2XUO-k-yjwvqi_DNuf",
      "name" : "import_ts",
      "exprId" : 3899
    } ],
    "destination" : {
      "port" : "Dz0WcZT7Bz1oPjYYQdwGn",
      "name" : "import_ts",
      "exprId" : 3899
    }
  }, {
    "sources" : [ {
      "port" : "IPn2XUO-k-yjwvqi_DNuf",
      "name" : "tran_type",
      "exprId" : 3897
    }, {
      "port" : "IPn2XUO-k-yjwvqi_DNuf",
      "name" : "tran_amount",
      "exprId" : 3896
    } ],
    "destination" : {
      "port" : "Dz0WcZT7Bz1oPjYYQdwGn",
      "name" : "signed_tran_amount",
      "exprId" : 3907
    },
    "transformation" : "CASE WHEN (`tran_type` = 'DEBIT') THEN (- `tran_amount`) ELSE `tran_amount` END"
  } ],
  "inputs" : {
    "IPn2XUO-k-yjwvqi_DNuf" : {
      "columns" : [ {
        "name" : "acc_id",
        "exprId" : 3893
      }, {
        "name" : "tran_id",
        "exprId" : 3894
      }, {
        "name" : "business_date",
        "exprId" : 3895
      }, {
        "name" : "tran_amount",
        "exprId" : 3896
      }, {
        "name" : "tran_type",
        "exprId" : 3897
      }, {
        "name" : "tran_ts",
        "exprId" : 3898
      }, {
        "name" : "import_ts",
        "exprId" : 3899
      } ]
    }
  },
  "outputs" : {
    "Dz0WcZT7Bz1oPjYYQdwGn" : {
      "columns" : [ {
        "name" : "acc_id",
        "exprId" : 3893
      }, {
        "name" : "tran_id",
        "exprId" : 3894
      }, {
        "name" : "business_date",
        "exprId" : 3895
      }, {
        "name" : "tran_amount",
        "exprId" : 3896
      }, {
        "name" : "tran_type",
        "exprId" : 3897
      }, {
        "name" : "tran_ts",
        "exprId" : 3898
      }, {
        "name" : "import_ts",
        "exprId" : 3899
      }, {
        "name" : "signed_tran_amount",
        "exprId" : 3907
      } ]
    }
  }
}