{
  "name" : "WGv_pBjGBT1_UhY3WVLfT",
  "component" : "Source",
  "transformations" : [ {
    "sources" : [ {
      "port" : "",
      "name" : "acc_id",
      "exprId" : -1
    } ],
    "destination" : {
      "port" : "BvH5HOmvjAF82bSQlXA1x",
      "name" : "acc_id",
      "exprId" : 288
    }
  }, {
    "sources" : [ {
      "port" : "",
      "name" : "person_id",
      "exprId" : -1
    } ],
    "destination" : {
      "port" : "BvH5HOmvjAF82bSQlXA1x",
      "name" : "person_id",
      "exprId" : 289
    }
  }, {
    "sources" : [ {
      "port" : "",
      "name" : "product_id",
      "exprId" : -1
    } ],
    "destination" : {
      "port" : "BvH5HOmvjAF82bSQlXA1x",
      "name" : "product_id",
      "exprId" : 290
    }
  }, {
    "sources" : [ {
      "port" : "",
      "name" : "balance",
      "exprId" : -1
    } ],
    "destination" : {
      "port" : "BvH5HOmvjAF82bSQlXA1x",
      "name" : "balance",
      "exprId" : 291
    }
  }, {
    "sources" : [ {
      "port" : "",
      "name" : "business_date",
      "exprId" : -1
    } ],
    "destination" : {
      "port" : "BvH5HOmvjAF82bSQlXA1x",
      "name" : "business_date",
      "exprId" : 292
    }
  }, {
    "sources" : [ {
      "port" : "",
      "name" : "import_ts",
      "exprId" : -1
    } ],
    "destination" : {
      "port" : "BvH5HOmvjAF82bSQlXA1x",
      "name" : "import_ts",
      "exprId" : 293
    }
  } ]
}